{
    "display": {
        "icon": {
            "item": "apples:itemapplelava"
        },
        "title": { 
            "translate": "Lava Apple"
        },
        "description": {
            "translate": ""
        },
        "show_toast": true
    },
    "parent": "apples:root",
    "criteria": {
        "root": {
            "trigger": "minecraft:inventory_changed",
            "conditions": {
                "items": [
                    {
                        "item": "apples:itemapplelava"
                    }
                ]
            }
        }
    }
}